{
  "indexes": [
    {
      "collectionGroup": "articles",
      "queryScope": "COLLECTION",
      "fields": [
        {
          "fieldPath": "category",
          "order": "ASCENDING"
        },
        {
          "fieldPath": "published",
          "order": "ASCENDING"
        },
        {
          "fieldPath": "createdAt",
          "order": "DESCENDING"
        }
      ]
    },
    {
      "collectionGroup": "articles",
      "queryScope": "COLLECTION",
      "fields": [
        {
          "fieldPath": "featured",
          "order": "ASCENDING"
        },
        {
          "fieldPath": "published",
          "order": "ASCENDING"
        },
        {
          "fieldPath": "createdAt",
          "order": "DESCENDING"
        }
      ]
    },
    {
      "collectionGroup": "articles",
      "queryScope": "COLLECTION",
      "fields": [
        {
          "fieldPath": "published",
          "order": "ASCENDING"
        },
        {
          "fieldPath": "createdAt",
          "order": "DESCENDING"
        }
      ]
    },
    {
      "collectionGroup": "campaigns",
      "queryScope": "COLLECTION",
      "fields": [
        {
          "fieldPath": "status",
          "order": "ASCENDING"
        },
        {
          "fieldPath": "scheduledFor",
          "order": "ASCENDING"
        }
      ]
    },
    {
      "collectionGroup": "comments",
      "queryScope": "COLLECTION_GROUP",
      "fields": [
        {
          "fieldPath": "userId",
          "order": "ASCENDING"
        },
        {
          "fieldPath": "timestamp",
          "order": "DESCENDING"
        }
      ]
    },
    {
      "collectionGroup": "emailTasks",
      "queryScope": "COLLECTION",
      "fields": [
        {
          "fieldPath": "status",
          "order": "ASCENDING"
        },
        {
          "fieldPath": "createdAt",
          "order": "ASCENDING"
        }
      ]
    },
    {
      "collectionGroup": "news",
      "queryScope": "COLLECTION",
      "fields": [
        {
          "fieldPath": "category",
          "order": "ASCENDING"
        },
        {
          "fieldPath": "createdAt",
          "order": "DESCENDING"
        }
      ]
    },
    {
      "collectionGroup": "sections",
      "queryScope": "COLLECTION",
      "fields": [
        {
          "fieldPath": "active",
          "order": "ASCENDING"
        },
        {
          "fieldPath": "name",
          "order": "ASCENDING"
        }
      ]
    },
    {
      "collectionGroup": "sections",
      "queryScope": "COLLECTION",
      "fields": [
        {
          "fieldPath": "active",
          "order": "ASCENDING"
        },
        {
          "fieldPath": "order",
          "order": "ASCENDING"
        }
      ]
    },
    {
      "collectionGroup": "tracking",
      "queryScope": "COLLECTION",
      "fields": [
        {
          "fieldPath": "subscriberId",
          "order": "ASCENDING"
        },
        {
          "fieldPath": "sentAt",
          "order": "DESCENDING"
        }
      ]
    }
  ],
  "fieldOverrides": []
}